CHANGELOG.md
LICENSE
MANIFEST.in
README.md
setup.py
csdncommenter/__init__.py
csdncommenter/csdncommenter.py
csdncommenter.egg-info/PKG-INFO
csdncommenter.egg-info/SOURCES.txt
csdncommenter.egg-info/dependency_links.txt
csdncommenter.egg-info/entry_points.txt
csdncommenter.egg-info/requires.txt
csdncommenter.egg-info/top_level.txt