Metadata-Version: 1.1
Name: csdncommenter
Version: 0.0.4
Summary: CSDN 已下载资源自动批量评论脚本
Home-page: https://github.com/mzlogin/csdncommenter
Author: Zhuang Ma
Author-email: chumpma@gmail.com
License: MIT
Keywords: csdn resource auto commenter
Platform: UNKNOWN
Classifier: Development Status :: 2 - Pre-Alpha
Classifier: Intended Audience :: Developers
Classifier: Topic :: Utilities
Classifier: License :: OSI Approved :: MIT License
Classifier: Programming Language :: Python :: 2
Classifier: Programming Language :: Python :: 2.6
Classifier: Programming Language :: Python :: 2.7
